core/__init__.py
core/adapters.py
core/custom_ai.py
core/custom_source.py
core/db_adapter.py
core/engine.py
core/migrator.py
core/rush_client.py
core/rush_discovery.py
core/rush_parser.py
core/rush_protocol.py
core/rush_protocols.py
core/rush_server.py
core/rush_trust.py
core/security.py
core/updater.py
rush_api-3.0.1.dist-info/licenses/LICENSE
rush_api-3.0.1.dist-info/METADATA
rush_api-3.0.1.dist-info/WHEEL
rush_api-3.0.1.dist-info/top_level.txt
rush_api-3.0.1.dist-info/RECORD
