Metadata-Version: 2.4
Name: rush-api
Version: 3.0.1
Summary: The Universal API Framework. High-performance Custom JSON-over-TCP Protocol. Zero Dependencies.
Author: Rushabh Mavani
Author-email: rushabhmavani01@gmail.com
Keywords: tcp api json protocol high-performance zero-dependency rush
Classifier: Development Status :: 5 - Production/Stable
Classifier: Intended Audience :: Developers
Classifier: License :: OSI Approved :: MIT License
Classifier: Programming Language :: Python :: 3
Classifier: Topic :: Internet :: WWW/HTTP
Classifier: Topic :: Software Development :: Libraries :: Python Modules
Requires-Python: >=3.8
License-File: LICENSE
Dynamic: author
Dynamic: author-email
Dynamic: classifier
Dynamic: description
Dynamic: description-content-type
Dynamic: keywords
Dynamic: license-file
Dynamic: requires-python
Dynamic: summary
